papilv_filemeta/__init__.py
papilv_filemeta/cli.py
papilv_filemeta/database.py
papilv_filemeta/metadata_manager.py
papilv_filemeta/models.py
papilv_filemeta/utils.py
papilv_filemeta-0.1.1.dist-info/METADATA
papilv_filemeta-0.1.1.dist-info/WHEEL
papilv_filemeta-0.1.1.dist-info/entry_points.txt
papilv_filemeta-0.1.1.dist-info/RECORD
